DESCRIPTION.rst
MANIFEST.in
setup.py
energenie/__init__.py
energenie/energenie.py
energenie.egg-info/PKG-INFO
energenie.egg-info/SOURCES.txt
energenie.egg-info/dependency_links.txt
energenie.egg-info/requires.txt
energenie.egg-info/top_level.txt