Metadata-Version: 1.1
Name: energenie
Version: 0.2.2
Summary: Remotely control power sockets from the Raspberry Pi
Home-page: https://github.com/bennuttall/energenie
Author: Ben Nuttall
Author-email: ben@raspberrypi.org
License: BSD
Keywords: energenie,raspberrypi
Platform: UNKNOWN
Classifier: Development Status :: 4 - Beta
Classifier: Topic :: Home Automation
Classifier: License :: OSI Approved :: BSD License
